{
  "root_name": "Beel",
  "rank": 3,
  "power_base": 100.0,
  "power_base_step": 0.25,
  "power_plv": 1.0,
  "power_plv_step": 0.1,
  "crit": 0.0,
  "crit_damage": 0.0,
  "health_base": 150.0,
  "health_base_step": 0.0,
  "health_plv": 0.0,
  "health_plv_step": 0.0,
  "speed_base": 95.0,
  "speed_step": 0.05,
  "armor": 20.0,
  "magic_resist": 35.0,
  "attack_type": 1,
  "classes": [
    4
  ],
  "skill_name": "Ultimate Ghost",
  "start_fury": 0,
  "max_fury": 20,
  "skill_params": [
    5.0
  ]
}
