{
  "root_name": "Scrub",
  "rank": 0,
  "power_base": 50.0,
  "power_base_step": 0.2,
  "power_plv": 1.0,
  "power_plv_step": 0.001,
  "crit": 0.0,
  "crit_damage": 0.0,
  "health_base": 320.0,
  "health_base_step": 0.5,
  "health_plv": 2.8,
  "health_plv_step": 0.003,
  "speed_base": 80.0,
  "speed_step": 0.05,
  "armor": 30.0,
  "magic_resist": 20.0,
  "attack_type": 0,
  "classes": [
    8
  ],
  "skill_name": "Scrub Attack",
  "start_fury": 0,
  "max_fury": 20,
  "skill_params": [
    1.5,
    0.5
  ]
}
